rio_client/__init__.py
rio_client/base.py
rio_client/delay.py
rio_client/dump.py
rio_client/parser.py
rio_client/retry.py
rio_client/contrib/__init__.py
rio_client/contrib/flask.py
rio_client/contrib/scrapy.py
rio_client/dump/__init__.py
rio_client/dump/redis.py
rio_client/transports/__init__.py
rio_client/transports/base.py
rio_client/transports/requests.py
rio_client-0.3.0.dist-info/DESCRIPTION.rst
rio_client-0.3.0.dist-info/METADATA
rio_client-0.3.0.dist-info/RECORD
rio_client-0.3.0.dist-info/WHEEL
rio_client-0.3.0.dist-info/metadata.json
rio_client-0.3.0.dist-info/top_level.txt
