Metadata-Version: 2.0
Name: rio-client
Version: 0.3.0
Summary: Client for Rio.
Home-page: https://github.com/soasme/rio-client
Author: Ju Lin
Author-email: soasme@gmail.com
License: MIT
Keywords: rio
Platform: UNKNOWN
Classifier: Development Status :: 2 - Pre-Alpha
Classifier: Intended Audience :: Developers
Classifier: Natural Language :: English
Classifier: Programming Language :: Python :: 2
Classifier: Programming Language :: Python :: 2.6
Classifier: Programming Language :: Python :: 2.7
Classifier: Programming Language :: Python :: 3
Classifier: Programming Language :: Python :: 3.3
Classifier: Programming Language :: Python :: 3.4
Classifier: Programming Language :: Python :: 3.5
Requires-Dist: requests (>=2.9.1)
